psyki/__init__.py
psyki/_logging.py
psyki/fairness/__init__.py
psyki/fairness/fauci/__init__.py
psyki/fairness/fauci/tf_metric.py
psyki/fuzzifiers/__init__.py
psyki/fuzzifiers/lukasciewicz/__init__.py
psyki/fuzzifiers/netbuilder/__init__.py
psyki/fuzzifiers/towell/__init__.py
psyki/logic/__init__.py
psyki/logic/operators/__init__.py
psyki/logic/prolog/__init__.py
psyki/qos/__init__.py
psyki/qos/data.py
psyki/qos/energy.py
psyki/qos/latency.py
psyki/qos/memory.py
psyki/qos/utils.py
psyki/ski/__init__.py
psyki/ski/kbann/__init__.py
psyki/ski/kill/__init__.py
psyki/ski/kins/__init__.py
psyki/utils/__init__.py
psyki/utils/__main__.py
psyki/utils/exceptions/__init__.py
psyki/wiki/__init__.py
psyki/wiki/__main__.py
psyki-0.4.3.dist-info/LICENSE
psyki-0.4.3.dist-info/METADATA
psyki-0.4.3.dist-info/WHEEL
psyki-0.4.3.dist-info/RECORD
