Metadata-Version: 2.1
Name: psyki
Version: 0.4.3
Summary: PSyKI: a (Python) platform for symbolic knowledge injection
License: Apache2.0
Author: Matteo Magnini
Author-email: matteo.magnini@unibo.it
Requires-Python: ==3.9.13
Classifier: License :: Other/Proprietary License
Classifier: Programming Language :: Python :: 3
Requires-Dist: 2ppy (>=0.4.1,<0.5.0)
Requires-Dist: codecarbon (==2.2.4)
Requires-Dist: pandas (==1.4.2)
Requires-Dist: prometheus-client (>=0.21.0,<0.22.0)
Requires-Dist: scikit-learn (==1.0.2)
Requires-Dist: tensorflow (==2.14.1)
Requires-Dist: tensorflow-macos (==2.14.1) ; sys_platform == "darwin"
